{
  "kind": "singleType",
  "collectionName": "works",
  "info": {
    "name": "Work"
  },
  "options": {
    "increments": true,
    "timestamps": true
  },
  "attributes": {
    "metaTitle": {
      "type": "string"
    },
    "metaDescription": {
      "type": "string"
    },
    "backgroundText": {
      "type": "string"
    },
    "tabletColumnSize": {
      "type": "string"
    },
    "tabletRowSize": {
      "type": "string"
    },
    "mobileColumnSize": {
      "type": "string"
    },
    "mobileRowSize": {
      "type": "string"
    },
    "desktopColumnSize": {
      "type": "string"
    },
    "desktopRowSize": {
      "type": "string"
    }
  }
}
